ext_targets
