Metadata-Version: 1.0
Name: setuptools-bin-targets
Version: 1.1
Summary: An add-on for setuptools to simplify building executables and static libraries
Home-page: https://gitlab.alelec.net/corona/cfficloak
Author: Andrew Leech
Author-email: andrew@alelec.net
License: UNKNOWN
Platform: UNKNOWN
